unstar/__init__.py
unstar/exceptions.py
unstar/main.py
unstar/stars.py
unstar-0.1.0.dist-info/METADATA
unstar-0.1.0.dist-info/WHEEL
unstar-0.1.0.dist-info/entry_points.txt
unstar-0.1.0.dist-info/licenses/LICENSE
unstar-0.1.0.dist-info/RECORD
