Metadata-Version: 2.4
Name: unstar
Version: 0.1.0
Summary: Simple script to automate the removal of GitHub stars
Project-URL: Homepage, https://github.com/forkdo/unstar
Project-URL: Repository, https://github.com/forkdo/unstar
Project-URL: Issues, https://github.com/forkdo/unstar/issues
Author-email: Jetsung Chan <i@jetsung.com>
License-Expression: Apache-2.0
License-File: LICENSE
Keywords: github,unstar,unstar-github,unstar-github-stars
Classifier: Development Status :: 4 - Beta
Classifier: Intended Audience :: Developers
Classifier: License :: OSI Approved :: Apache Software License
Classifier: Programming Language :: Python :: 3
Classifier: Programming Language :: Python :: 3.8
Classifier: Programming Language :: Python :: 3.9
Classifier: Programming Language :: Python :: 3.10
Classifier: Programming Language :: Python :: 3.11
Classifier: Programming Language :: Python :: 3.12
Classifier: Programming Language :: Python :: 3.13
Classifier: Programming Language :: Python :: 3.14
Requires-Python: >=3.8
Requires-Dist: requests>=2.31.0
